genologics/__init__.py
genologics/entities.py
genologics/lims.py
pyclarity_lims/__init__.py
pyclarity_lims/constants.py
pyclarity_lims/descriptors.py
pyclarity_lims/entities.py
pyclarity_lims/lims.py
pyclarity_lims-0.4.6.dist-info/DESCRIPTION.rst
pyclarity_lims-0.4.6.dist-info/METADATA
pyclarity_lims-0.4.6.dist-info/RECORD
pyclarity_lims-0.4.6.dist-info/WHEEL
pyclarity_lims-0.4.6.dist-info/metadata.json
pyclarity_lims-0.4.6.dist-info/top_level.txt
